pydepdetective/__init__.py
pydepdetective/main.py
pydepdetective-0.1.1.dist-info/METADATA
pydepdetective-0.1.1.dist-info/WHEEL
pydepdetective-0.1.1.dist-info/entry_points.txt
pydepdetective-0.1.1.dist-info/licenses/LICENSE
pydepdetective-0.1.1.dist-info/RECORD
