Metadata-Version: 2.3
Name: pydepdetective
Version: 0.1.1
Summary: A tool to automatically detect and install Python dependencies
Project-URL: Homepage, https://github.com/Felixdiamond/pydepdetective
Project-URL: Bug Tracker, https://github.com/Felixdiamond/pydepdetective/issues
Author-email: Felix Dawodu <diamondfelix006@gmail.com>
License-File: LICENSE
Classifier: License :: OSI Approved :: MIT License
Classifier: Operating System :: OS Independent
Classifier: Programming Language :: Python :: 3
Requires-Python: >=3.7
